[{"source": "/content/seven.pdf", "page": 1}, {"source": "/content/seven.pdf", "page": 1}, {"source": "/content/seven.pdf", "page": 1}, {"source": "/content/seven.pdf", "page": 1}, {"source": "/content/seven.pdf", "page": 1}, {"source": "/content/seven.pdf", "page": 1}, {"source": "/content/seven.pdf", "page": 1}, {"source": "/content/seven.pdf", "page": 2}, {"source": "/content/seven.pdf", "page": 2}, {"source": "/content/seven.pdf", "page": 2}, {"source": "/content/seven.pdf", "page": 2}, {"source": "/content/seven.pdf", "page": 2}, {"source": "/content/seven.pdf", "page": 2}, {"source": "/content/seven.pdf", "page": 2}, {"source": "/content/seven.pdf", "page": 3}, {"source": "/content/seven.pdf", "page": 3}, {"source": "/content/seven.pdf", "page": 3}, {"source": "/content/seven.pdf", "page": 3}, {"source": "/content/seven.pdf", "page": 3}, {"source": "/content/seven.pdf", "page": 3}, {"source": "/content/seven.pdf", "page": 3}, {"source": "/content/seven.pdf", "page": 4}, {"source": "/content/seven.pdf", "page": 4}, {"source": "/content/seven.pdf", "page": 4}, {"source": "/content/seven.pdf", "page": 4}, {"source": "/content/seven.pdf", "page": 4}, {"source": "/content/seven.pdf", "page": 5}, {"source": "/content/seven.pdf", "page": 5}, {"source": "/content/seven.pdf", "page": 5}, {"source": "/content/seven.pdf", "page": 5}, {"source": "/content/seven.pdf", "page": 5}, {"source": "/content/seven.pdf", "page": 5}, {"source": "/content/seven.pdf", "page": 6}, {"source": "/content/seven.pdf", "page": 6}, {"source": "/content/seven.pdf", "page": 6}, {"source": "/content/seven.pdf", "page": 6}, {"source": "/content/seven.pdf", "page": 6}, {"source": "/content/seven.pdf", "page": 7}, {"source": "/content/seven.pdf", "page": 7}, {"source": "/content/seven.pdf", "page": 7}, {"source": "/content/seven.pdf", "page": 7}, {"source": "/content/seven.pdf", "page": 7}, {"source": "/content/seven.pdf", "page": 7}, {"source": "/content/seven.pdf", "page": 7}, {"source": "/content/seven.pdf", "page": 8}, {"source": "/content/seven.pdf", "page": 8}, {"source": "/content/seven.pdf", "page": 8}, {"source": "/content/seven.pdf", "page": 8}, {"source": "/content/seven.pdf", "page": 8}, {"source": "/content/seven.pdf", "page": 8}, {"source": "/content/seven.pdf", "page": 8}, {"source": "/content/seven.pdf", "page": 9}, {"source": "/content/seven.pdf", "page": 9}, {"source": "/content/seven.pdf", "page": 9}, {"source": "/content/seven.pdf", "page": 9}, {"source": "/content/seven.pdf", "page": 9}, {"source": "/content/seven.pdf", "page": 9}, {"source": "/content/seven.pdf", "page": 10}, {"source": "/content/seven.pdf", "page": 10}, {"source": "/content/seven.pdf", "page": 10}, {"source": "/content/seven.pdf", "page": 10}, {"source": "/content/seven.pdf", "page": 10}, {"source": "/content/seven.pdf", "page": 10}, {"source": "/content/seven.pdf", "page": 11}, {"source": "/content/seven.pdf", "page": 11}, {"source": "/content/seven.pdf", "page": 11}, {"source": "/content/seven.pdf", "page": 11}, {"source": "/content/seven.pdf", "page": 11}, {"source": "/content/seven.pdf", "page": 11}, {"source": "/content/seven.pdf", "page": 11}, {"source": "/content/seven.pdf", "page": 11}, {"source": "/content/seven.pdf", "page": 12}, {"source": "/content/seven.pdf", "page": 12}, {"source": "/content/seven.pdf", "page": 12}, {"source": "/content/seven.pdf", "page": 12}, {"source": "/content/seven.pdf", "page": 12}, {"source": "/content/seven.pdf", "page": 12}, {"source": "/content/seven.pdf", "page": 12}, {"source": "/content/seven.pdf", "page": 12}, {"source": "/content/seven.pdf", "page": 13}, {"source": "/content/seven.pdf", "page": 13}, {"source": "/content/seven.pdf", "page": 13}, {"source": "/content/seven.pdf", "page": 13}, {"source": "/content/seven.pdf", "page": 14}, {"source": "/content/seven.pdf", "page": 14}, {"source": "/content/seven.pdf", "page": 14}, {"source": "/content/seven.pdf", "page": 14}, {"source": "/content/seven.pdf", "page": 14}, {"source": "/content/seven.pdf", "page": 14}, {"source": "/content/seven.pdf", "page": 14}, {"source": "/content/seven.pdf", "page": 14}, {"source": "/content/seven.pdf", "page": 15}, {"source": "/content/seven.pdf", "page": 15}, {"source": "/content/seven.pdf", "page": 15}, {"source": "/content/seven.pdf", "page": 15}, {"source": "/content/seven.pdf", "page": 15}, {"source": "/content/seven.pdf", "page": 15}, {"source": "/content/seven.pdf", "page": 15}, {"source": "/content/seven.pdf", "page": 16}, {"source": "/content/seven.pdf", "page": 16}, {"source": "/content/seven.pdf", "page": 16}, {"source": "/content/seven.pdf", "page": 16}, {"source": "/content/seven.pdf", "page": 16}, {"source": "/content/seven.pdf", "page": 16}, {"source": "/content/seven.pdf", "page": 17}, {"source": "/content/seven.pdf", "page": 17}, {"source": "/content/seven.pdf", "page": 17}, {"source": "/content/seven.pdf", "page": 18}, {"source": "/content/seven.pdf", "page": 18}, {"source": "/content/seven.pdf", "page": 18}, {"source": "/content/seven.pdf", "page": 18}, {"source": "/content/seven.pdf", "page": 18}, {"source": "/content/seven.pdf", "page": 18}, {"source": "/content/seven.pdf", "page": 19}, {"source": "/content/seven.pdf", "page": 19}, {"source": "/content/seven.pdf", "page": 19}, {"source": "/content/seven.pdf", "page": 19}, {"source": "/content/seven.pdf", "page": 19}, {"source": "/content/seven.pdf", "page": 20}, {"source": "/content/seven.pdf", "page": 20}, {"source": "/content/seven.pdf", "page": 20}, {"source": "/content/seven.pdf", "page": 20}, {"source": "/content/seven.pdf", "page": 20}, {"source": "/content/seven.pdf", "page": 21}, {"source": "/content/seven.pdf", "page": 21}, {"source": "/content/seven.pdf", "page": 21}, {"source": "/content/seven.pdf", "page": 21}, {"source": "/content/seven.pdf", "page": 21}, {"source": "/content/seven.pdf", "page": 21}, {"source": "/content/seven.pdf", "page": 21}, {"source": "/content/seven.pdf", "page": 21}, {"source": "/content/seven.pdf", "page": 22}, {"source": "/content/seven.pdf", "page": 22}, {"source": "/content/seven.pdf", "page": 22}, {"source": "/content/seven.pdf", "page": 22}, {"source": "/content/seven.pdf", "page": 22}, {"source": "/content/seven.pdf", "page": 22}, {"source": "/content/seven.pdf", "page": 23}, {"source": "/content/seven.pdf", "page": 23}, {"source": "/content/seven.pdf", "page": 23}, {"source": "/content/seven.pdf", "page": 23}, {"source": "/content/seven.pdf", "page": 24}, {"source": "/content/seven.pdf", "page": 24}, {"source": "/content/seven.pdf", "page": 24}, {"source": "/content/seven.pdf", "page": 24}, {"source": "/content/seven.pdf", "page": 24}, {"source": "/content/seven.pdf", "page": 25}, {"source": "/content/seven.pdf", "page": 25}, {"source": "/content/seven.pdf", "page": 25}, {"source": "/content/seven.pdf", "page": 25}, {"source": "/content/seven.pdf", "page": 25}, {"source": "/content/seven.pdf", "page": 26}, {"source": "/content/seven.pdf", "page": 26}, {"source": "/content/seven.pdf", "page": 26}, {"source": "/content/seven.pdf", "page": 26}, {"source": "/content/seven.pdf", "page": 26}, {"source": "/content/seven.pdf", "page": 26}, {"source": "/content/seven.pdf", "page": 26}, {"source": "/content/seven.pdf", "page": 27}, {"source": "/content/seven.pdf", "page": 27}, {"source": "/content/seven.pdf", "page": 27}, {"source": "/content/seven.pdf", "page": 27}, {"source": "/content/seven.pdf", "page": 27}, {"source": "/content/seven.pdf", "page": 27}, {"source": "/content/seven.pdf", "page": 28}, {"source": "/content/seven.pdf", "page": 28}, {"source": "/content/seven.pdf", "page": 28}, {"source": "/content/seven.pdf", "page": 28}, {"source": "/content/seven.pdf", "page": 28}, {"source": "/content/seven.pdf", "page": 29}, {"source": "/content/seven.pdf", "page": 29}, {"source": "/content/seven.pdf", "page": 29}, {"source": "/content/seven.pdf", "page": 29}, {"source": "/content/seven.pdf", "page": 29}, {"source": "/content/seven.pdf", "page": 29}, {"source": "/content/seven.pdf", "page": 30}, {"source": "/content/seven.pdf", "page": 30}, {"source": "/content/seven.pdf", "page": 30}, {"source": "/content/seven.pdf", "page": 30}, {"source": "/content/seven.pdf", "page": 30}, {"source": "/content/seven.pdf", "page": 30}, {"source": "/content/seven.pdf", "page": 31}, {"source": "/content/seven.pdf", "page": 31}, {"source": "/content/seven.pdf", "page": 31}, {"source": "/content/seven.pdf", "page": 31}, {"source": "/content/seven.pdf", "page": 31}, {"source": "/content/seven.pdf", "page": 31}, {"source": "/content/seven.pdf", "page": 32}, {"source": "/content/seven.pdf", "page": 32}, {"source": "/content/seven.pdf", "page": 32}, {"source": "/content/seven.pdf", "page": 32}, {"source": "/content/seven.pdf", "page": 32}, {"source": "/content/seven.pdf", "page": 32}, {"source": "/content/seven.pdf", "page": 32}, {"source": "/content/seven.pdf", "page": 33}, {"source": "/content/seven.pdf", "page": 33}, {"source": "/content/seven.pdf", "page": 33}, {"source": "/content/seven.pdf", "page": 33}, {"source": "/content/seven.pdf", "page": 33}, {"source": "/content/seven.pdf", "page": 33}, {"source": "/content/seven.pdf", "page": 34}, {"source": "/content/seven.pdf", "page": 34}, {"source": "/content/seven.pdf", "page": 34}, {"source": "/content/seven.pdf", "page": 34}, {"source": "/content/seven.pdf", "page": 34}, {"source": "/content/seven.pdf", "page": 34}, {"source": "/content/seven.pdf", "page": 35}, {"source": "/content/seven.pdf", "page": 35}, {"source": "/content/seven.pdf", "page": 35}, {"source": "/content/seven.pdf", "page": 35}, {"source": "/content/seven.pdf", "page": 35}, {"source": "/content/seven.pdf", "page": 36}, {"source": "/content/seven.pdf", "page": 36}, {"source": "/content/seven.pdf", "page": 36}, {"source": "/content/seven.pdf", "page": 36}, {"source": "/content/seven.pdf", "page": 36}, {"source": "/content/seven.pdf", "page": 36}, {"source": "/content/seven.pdf", "page": 37}, {"source": "/content/seven.pdf", "page": 37}, {"source": "/content/seven.pdf", "page": 37}, {"source": "/content/seven.pdf", "page": 37}, {"source": "/content/seven.pdf", "page": 37}, {"source": "/content/seven.pdf", "page": 37}, {"source": "/content/seven.pdf", "page": 38}, {"source": "/content/seven.pdf", "page": 38}, {"source": "/content/seven.pdf", "page": 38}, {"source": "/content/seven.pdf", "page": 38}, {"source": "/content/seven.pdf", "page": 38}, {"source": "/content/seven.pdf", "page": 39}, {"source": "/content/seven.pdf", "page": 39}, {"source": "/content/seven.pdf", "page": 39}, {"source": "/content/seven.pdf", "page": 39}, {"source": "/content/seven.pdf", "page": 39}, {"source": "/content/seven.pdf", "page": 39}, {"source": "/content/seven.pdf", "page": 39}, {"source": "/content/seven.pdf", "page": 40}, {"source": "/content/seven.pdf", "page": 40}, {"source": "/content/seven.pdf", "page": 40}, {"source": "/content/seven.pdf", "page": 40}, {"source": "/content/seven.pdf", "page": 40}, {"source": "/content/seven.pdf", "page": 40}, {"source": "/content/seven.pdf", "page": 41}, {"source": "/content/seven.pdf", "page": 41}, {"source": "/content/seven.pdf", "page": 41}, {"source": "/content/seven.pdf", "page": 41}, {"source": "/content/seven.pdf", "page": 41}, {"source": "/content/seven.pdf", "page": 41}, {"source": "/content/seven.pdf", "page": 42}, {"source": "/content/seven.pdf", "page": 42}, {"source": "/content/seven.pdf", "page": 42}, {"source": "/content/seven.pdf", "page": 42}, {"source": "/content/seven.pdf", "page": 42}, {"source": "/content/seven.pdf", "page": 43}, {"source": "/content/seven.pdf", "page": 43}, {"source": "/content/seven.pdf", "page": 43}, {"source": "/content/seven.pdf", "page": 43}, {"source": "/content/seven.pdf", "page": 43}, {"source": "/content/seven.pdf", "page": 43}, {"source": "/content/seven.pdf", "page": 44}, {"source": "/content/seven.pdf", "page": 44}, {"source": "/content/seven.pdf", "page": 44}, {"source": "/content/seven.pdf", "page": 44}, {"source": "/content/seven.pdf", "page": 45}, {"source": "/content/seven.pdf", "page": 45}, {"source": "/content/seven.pdf", "page": 45}, {"source": "/content/seven.pdf", "page": 45}, {"source": "/content/seven.pdf", "page": 45}, {"source": "/content/seven.pdf", "page": 45}, {"source": "/content/seven.pdf", "page": 46}, {"source": "/content/seven.pdf", "page": 46}, {"source": "/content/seven.pdf", "page": 46}, {"source": "/content/seven.pdf", "page": 46}, {"source": "/content/seven.pdf", "page": 46}, {"source": "/content/seven.pdf", "page": 46}, {"source": "/content/seven.pdf", "page": 46}, {"source": "/content/seven.pdf", "page": 47}, {"source": "/content/seven.pdf", "page": 47}, {"source": "/content/seven.pdf", "page": 47}, {"source": "/content/seven.pdf", "page": 47}, {"source": "/content/seven.pdf", "page": 47}, {"source": "/content/seven.pdf", "page": 48}, {"source": "/content/seven.pdf", "page": 48}, {"source": "/content/seven.pdf", "page": 48}, {"source": "/content/seven.pdf", "page": 48}, {"source": "/content/seven.pdf", "page": 48}, {"source": "/content/seven.pdf", "page": 48}, {"source": "/content/seven.pdf", "page": 49}, {"source": "/content/seven.pdf", "page": 49}, {"source": "/content/seven.pdf", "page": 49}, {"source": "/content/seven.pdf", "page": 49}, {"source": "/content/seven.pdf", "page": 49}, {"source": "/content/seven.pdf", "page": 49}, {"source": "/content/seven.pdf", "page": 49}, {"source": "/content/seven.pdf", "page": 50}, {"source": "/content/seven.pdf", "page": 50}, {"source": "/content/seven.pdf", "page": 50}, {"source": "/content/seven.pdf", "page": 50}, {"source": "/content/seven.pdf", "page": 50}, {"source": "/content/seven.pdf", "page": 51}, {"source": "/content/seven.pdf", "page": 51}, {"source": "/content/seven.pdf", "page": 51}, {"source": "/content/seven.pdf", "page": 51}, {"source": "/content/seven.pdf", "page": 51}, {"source": "/content/seven.pdf", "page": 52}, {"source": "/content/seven.pdf", "page": 52}, {"source": "/content/seven.pdf", "page": 52}, {"source": "/content/seven.pdf", "page": 52}, {"source": "/content/seven.pdf", "page": 52}, {"source": "/content/seven.pdf", "page": 52}, {"source": "/content/seven.pdf", "page": 52}, {"source": "/content/seven.pdf", "page": 52}, {"source": "/content/seven.pdf", "page": 53}, {"source": "/content/seven.pdf", "page": 53}, {"source": "/content/seven.pdf", "page": 53}, {"source": "/content/seven.pdf", "page": 53}, {"source": "/content/seven.pdf", "page": 53}, {"source": "/content/seven.pdf", "page": 53}, {"source": "/content/seven.pdf", "page": 53}, {"source": "/content/seven.pdf", "page": 53}, {"source": "/content/seven.pdf", "page": 54}, {"source": "/content/seven.pdf", "page": 54}, {"source": "/content/seven.pdf", "page": 54}]